os_tool/__init__.py
os_tool/os_01.py
os_tool/os_test.py
os_tool/test01.py
os_toolkit/__init__.py
os_toolkit/cant_use_ost.py
os_toolkit/fix_bug_ost.py
os_toolkit/sandbox1_ost.py
os_toolkit/test01.py
os_toolkit/utils_ost.py
os_toolkit-0.1.4.dist-info/METADATA
os_toolkit-0.1.4.dist-info/WHEEL
os_toolkit-0.1.4.dist-info/top_level.txt
os_toolkit-0.1.4.dist-info/RECORD
